scinumtools/__init__.py
scinumtools/cached_function.py
scinumtools/data_combination.py
scinumtools/data_plot_grid.py
scinumtools/image_metadata.py
scinumtools/normalize_data.py
scinumtools/parameter_table.py
scinumtools/progress_bar.py
scinumtools/row_collector.py
scinumtools/stopwatch.py
scinumtools/thumbnail_image.py
scinumtools/dip/__init__.py
scinumtools/dip/dip.py
scinumtools/dip/environment.py
scinumtools/dip/settings.py
scinumtools/dip/config/__init__.py
scinumtools/dip/config/export.py
scinumtools/dip/config/export_bash.py
scinumtools/dip/config/export_c.py
scinumtools/dip/config/export_cpp.py
scinumtools/dip/config/export_fortran.py
scinumtools/dip/config/export_json.py
scinumtools/dip/config/export_rust.py
scinumtools/dip/config/export_toml.py
scinumtools/dip/config/export_yaml.py
scinumtools/dip/datatypes/__init__.py
scinumtools/dip/datatypes/type.py
scinumtools/dip/datatypes/type_boolean.py
scinumtools/dip/datatypes/type_float.py
scinumtools/dip/datatypes/type_integer.py
scinumtools/dip/datatypes/type_number.py
scinumtools/dip/datatypes/type_string.py
scinumtools/dip/docs/__init__.py
scinumtools/dip/docs/documentation.py
scinumtools/dip/docs/item_import.py
scinumtools/dip/docs/item_injection.py
scinumtools/dip/docs/item_node.py
scinumtools/dip/docs/item_parameter.py
scinumtools/dip/docs/item_source.py
scinumtools/dip/docs/item_unit.py
scinumtools/dip/docs/settings.py
scinumtools/dip/docs/html/export.py
scinumtools/dip/docs/html/layout.html
scinumtools/dip/docs/html/section_parameters.py
scinumtools/dip/docs/html/section_references.py
scinumtools/dip/docs/html/section_settings.py
scinumtools/dip/docs/html/settings.py
scinumtools/dip/docs/pdf/__init__.py
scinumtools/dip/docs/pdf/export.py
scinumtools/dip/docs/pdf/imports.py
scinumtools/dip/docs/pdf/injections.py
scinumtools/dip/docs/pdf/node.py
scinumtools/dip/docs/pdf/parameters.py
scinumtools/dip/docs/pdf/settings.py
scinumtools/dip/docs/pdf/sources.py
scinumtools/dip/docs/pdf/types.py
scinumtools-2.19.4.dist-info/METADATA
scinumtools-2.19.4.dist-info/WHEEL
scinumtools-2.19.4.dist-info/licenses/LICENSE
scinumtools-2.19.4.dist-info/RECORD
