Metadata-Version: 2.3
Name: scinumtools
Version: 2.19.4
Summary: Set of most frequently used tools for a rapid numerical code development in Python.
Project-URL: Homepage, https://github.com/vrtulka23/scinumtools
Project-URL: Bug Tracker, https://github.com/vrtulka23/scinumtools/issues
Author-email: Ondrej Pego Jaura <vrtulka23@pm.me>
License-File: LICENSE
Classifier: License :: OSI Approved :: MIT License
Classifier: Operating System :: OS Independent
Classifier: Programming Language :: Python :: 3
Requires-Python: >=3.7
